{
  "main": {
    "id": "45d985b95a2976ac",
    "type": "split",
    "children": [
      {
        "id": "8732f0b1e2f9baea",
        "type": "tabs",
        "children": [
          {
            "id": "1b863e6d144c54eb",
            "type": "leaf",
            "state": {
              "type": "empty",
              "state": {}
            }
          }
        ]
      }
    ],
    "direction": "vertical"
  },
  "left": {
    "id": "186bdc3d2d59c454",
    "type": "split",
    "children": [
      {
        "id": "3bf40bc60ace80b7",
        "type": "tabs",
        "children": [
          {
            "id": "d1105a8dbea6f71a",
            "type": "leaf",
            "state": {
              "type": "file-explorer",
              "state": {
                "sortOrder": "byCreatedTimeReverse"
              }
            }
          },
          {
            "id": "c6b0b4b3fca5a931",
            "type": "leaf",
            "state": {
              "type": "search",
              "state": {
                "query": "",
                "matchingCase": false,
                "explainSearch": false,
                "collapseAll": false,
                "extraContext": false,
                "sortOrder": "alphabetical"
              }
            }
          },
          {
            "id": "9bb8cc880b287189",
            "type": "leaf",
            "state": {
              "type": "bookmarks",
              "state": {}
            }
          }
        ]
      }
    ],
    "direction": "horizontal",
    "width": 290.5
  },
  "right": {
    "id": "498eaa1305fa42be",
    "type": "split",
    "children": [
      {
        "id": "9a8b43e353c67b0f",
        "type": "tabs",
        "children": [
          {
            "id": "e2759de0c5cd30bf",
            "type": "leaf",
            "state": {
              "type": "backlink",
              "state": {
                "collapseAll": false,
                "extraContext": false,
                "sortOrder": "alphabetical",
                "showSearch": false,
                "searchQuery": "",
                "backlinkCollapsed": false,
                "unlinkedCollapsed": true
              }
            }
          },
          {
            "id": "bdc92d519658e7c2",
            "type": "leaf",
            "state": {
              "type": "outgoing-link",
              "state": {
                "linksCollapsed": false,
                "unlinkedCollapsed": true
              }
            }
          },
          {
            "id": "d28502e511a102e8",
            "type": "leaf",
            "state": {
              "type": "tag",
              "state": {
                "sortOrder": "frequency",
                "useHierarchy": true
              }
            }
          },
          {
            "id": "6bb929a5b493cbec",
            "type": "leaf",
            "state": {
              "type": "all-properties",
              "state": {
                "sortOrder": "frequency",
                "showSearch": false,
                "searchQuery": ""
              }
            }
          },
          {
            "id": "13631502f7a8d0e1",
            "type": "leaf",
            "state": {
              "type": "outline",
              "state": {}
            }
          }
        ]
      }
    ],
    "direction": "horizontal",
    "width": 300,
    "collapsed": true
  },
  "left-ribbon": {
    "hiddenItems": {
      "switcher:Open quick switcher": false,
      "graph:Open graph view": false,
      "canvas:Create new canvas": false,
      "daily-notes:Open today's daily note": false,
      "templates:Insert template": false,
      "command-palette:Open command palette": false,
      "table-editor-obsidian:Advanced Tables Toolbar": false
    }
  },
  "active": "1b863e6d144c54eb",
  "lastOpenFiles": [
    "645c93c1-8075-4a47-9d3b-c8bca7f44458_Export-9dd3b834-0a05-4bf8-a1b9-09818963f4b5/home 6aca0578b099438c92b98e817e51b3bb/университет e51112a4045b472b9434dba560c74b1c dd8423822791487db7ea5e569d9d9d09/архив предметов cf2f1fe7c4514bc9a75cc16a21a326d0/дискретная математика aa82726033204d5da35f36d699e7f764/лекции 940033f4a3474b0a8118c40198263d91/элементы теории множеств 02f8b163ece44ad89dbe06427d3d92fb.md",
    "645c93c1-8075-4a47-9d3b-c8bca7f44458_Export-9dd3b834-0a05-4bf8-a1b9-09818963f4b5/home 6aca0578b099438c92b98e817e51b3bb/университет e51112a4045b472b9434dba560c74b1c dd8423822791487db7ea5e569d9d9d09/архив предметов cf2f1fe7c4514bc9a75cc16a21a326d0/дискретная математика aa82726033204d5da35f36d699e7f764/лекции 940033f4a3474b0a8118c40198263d91/элементы логики 29d3ef7a3c9a4444b80d36d239ff3e28.md",
    "645c93c1-8075-4a47-9d3b-c8bca7f44458_Export-9dd3b834-0a05-4bf8-a1b9-09818963f4b5/home 6aca0578b099438c92b98e817e51b3bb/университет e51112a4045b472b9434dba560c74b1c dd8423822791487db7ea5e569d9d9d09/архив предметов cf2f1fe7c4514bc9a75cc16a21a326d0/дискретная математика aa82726033204d5da35f36d699e7f764/лекции 940033f4a3474b0a8118c40198263d91/комбинаторика cbcb25df375a478780d657f9bde03391.md",
    "645c93c1-8075-4a47-9d3b-c8bca7f44458_Export-9dd3b834-0a05-4bf8-a1b9-09818963f4b5/home 6aca0578b099438c92b98e817e51b3bb/университет e51112a4045b472b9434dba560c74b1c dd8423822791487db7ea5e569d9d9d09/архив предметов cf2f1fe7c4514bc9a75cc16a21a326d0/дискретная математика aa82726033204d5da35f36d699e7f764/дата тема 5dc43bf4c78d45d4a6ff8cfe3afcc257.md",
    "645c93c1-8075-4a47-9d3b-c8bca7f44458_Export-9dd3b834-0a05-4bf8-a1b9-09818963f4b5/home 6aca0578b099438c92b98e817e51b3bb/университет e51112a4045b472b9434dba560c74b1c dd8423822791487db7ea5e569d9d9d09/иконки 38fec84875b9412b8c4063cc1519dc8a.md",
    "645c93c1-8075-4a47-9d3b-c8bca7f44458_Export-9dd3b834-0a05-4bf8-a1b9-09818963f4b5/home 6aca0578b099438c92b98e817e51b3bb/университет e51112a4045b472b9434dba560c74b1c dd8423822791487db7ea5e569d9d9d09/архив предметов cf2f1fe7c4514bc9a75cc16a21a326d0.md",
    "645c93c1-8075-4a47-9d3b-c8bca7f44458_Export-9dd3b834-0a05-4bf8-a1b9-09818963f4b5/home 6aca0578b099438c92b98e817e51b3bb/университет e51112a4045b472b9434dba560c74b1c.md",
    "645c93c1-8075-4a47-9d3b-c8bca7f44458_Export-9dd3b834-0a05-4bf8-a1b9-09818963f4b5/home 6aca0578b099438c92b98e817e51b3bb/экстра 0bfc5f7db69f4d9c806d52824bdb6079.md",
    "645c93c1-8075-4a47-9d3b-c8bca7f44458_Export-9dd3b834-0a05-4bf8-a1b9-09818963f4b5/home 6aca0578b099438c92b98e817e51b3bb/genshin e8597651a7c145438dee6194f0c1cf32.md",
    "645c93c1-8075-4a47-9d3b-c8bca7f44458_Export-9dd3b834-0a05-4bf8-a1b9-09818963f4b5/home 6aca0578b099438c92b98e817e51b3bb/библиотека 058a122936b849ef80cadc0f240f3488.md",
    "645c93c1-8075-4a47-9d3b-c8bca7f44458_Export-9dd3b834-0a05-4bf8-a1b9-09818963f4b5/home 6aca0578b099438c92b98e817e51b3bb.md",
    "университет/1С лабы/1С лабы.md",
    "нео/справка/ИТС.md",
    "нео/справка/ПП1С.md",
    "университет/философия/24-09-09 философия пр 1.md",
    "нео/продажа/Чек-лист_к_встрече_ОМ_СЦ.docx",
    "нео/продажа/Встречи.pptx",
    "нео/продажа/вопросы_продаж_1С.doc",
    "нео/продажа",
    "нео/untitled folder",
    "университет/философия/24-09-02 философия лек 1.md",
    "университет/список дисциплин.md",
    "университет/1С лабы",
    "университет/архитектура/архитектура предприятий.md",
    "всякое/help.md",
    "университет/архитектура/архитектура 1.md",
    "университет/архитектура/архитектура 2.md",
    "университет/стандартизация/24-09-02 стандартизация 1.md",
    "университет/стандартизация/стандартизация, сертификация и управление качеством программного обеспечения.md",
    "университет/философия/философия.md",
    "университет/философия/материалы/Merab Mamardashvili philosophy.pdf",
    "университет/философия/материалы/Merab Mamardasvili philosophy.pdf",
    "университет/философия/Merab Mamardasvili philosophy.pdf",
    "университет/Merab Mamardasvili philosophy.pdf",
    "нео/справка/image.jpg",
    "нео/справка/механизм лицензирования.md",
    "нео/справка/день 2.md",
    "университет/философия/вложения/IMG_2336.jpeg",
    "университет/философия/вложения/IMG_2337.jpeg",
    "университет/философия/вложения/image.jpeg",
    "университет/философия/вложения/image 2.jpeg",
    "университет/философия/вложения/image 1.jpeg",
    "ктп/инструкция/Pasted image 20240806155254.png"
  ]
}